Workbook

Sheet Read me
A1: Card Run HQ -- master workbook
A2: Built 2026-08-16. Inventory is the master record; the eBay upload is generated from it.
A4: Photo to listing
A5: 1 | B5: Photograph the card, front and back, and send it to Claude.
A6: 2 | B6: Claude reads the set, number and parallel off the card and gives you a row for Inventory.
A7: 3 | B7: Tap the 'sold' link in that row to see what the card actually sells for, and put that in Market value.
A8: 4 | B8: Set Ask price. Est fees, Est net and Margin fill in on their own.
A9: 5 | B9: Run: python make_ebay_csv.py
A10: 6 | B10: In eBay, go to Seller Hub, Reports, Uploads, and download the template for Trading Card Singles.
A11: 7 | B11: Put that file in this folder as ebay-template.csv and run the script again -- it will match your template's header row exactly.
A12: 8 | B12: Upload the CSV it writes, then check the results report on the same page.
A14: The tabs
A15: Summary | B15: What it all adds up to: spent, held, sold, and whether it is working. Every figure is a formula over the other tabs, so nothing here can go stale -- if a number looks wrong, the row it came from is wrong.
A16: Audit | B16: What to fix before it costs you: cards held for review, a listing with no price or no photo, a title over 80 characters, a purchase with no receipt, a card that sold but is still marked in stock. All counts, all live. Zero down the column means the workbook is clean.
A17: Inventory | B17: Every card you own, one row each. This is the master -- everything else reads from it. Type into the white columns; the shaded ones work themselves out. The eBay title builds itself and Len turns red past 80 characters, which is eBay's hard limit.
A18: eBay upload | B18: Written for you by make_ebay_csv.py. Do not type here -- it gets rebuilt. It holds only the Inventory rows marked Unlisted.
A19: Purchases | B19: Every buy with its receipt -- boxes, singles, bulk lots, supplies. Put the same Lot ID here, on the Box log and on the cards that came out, and cost per card stops being a guess. Receipt file is the name you saved the photo or PDF under; keep it for the tax year and for disputes.
A20: Box log | B20: Every box and pack bought: where, when, what it cost with tax, how many cards came out and what they were worth. Net vs cost is the number that says whether ripping beat selling it sealed.
A21: Expenses | B21: The costs that are not a card: toploaders, mailers, postage, the scanner, subscriptions. These are what turn a gross profit into a real one and they are the first thing forgotten.
A22: Photos | B22: Which cards have a picture, with the picture in it -- run embed_photos.py and scroll it as a visual stock check. The URL column is what eBay fetches; it only works once the photos have been pushed, because the workbook carries links rather than the image files themselves.
A23: Sales | B23: What actually sold and what was left after fees. Profit is measured against cost basis, so allocate the box cost across the cards it produced -- Cost per card on the Box log gives you that figure.
A24: Reference | B24: The eBay codes the upload depends on, with where each one came from. Check this tab first if an upload gets rejected.
A26: Read this before the first upload
B27: eBay retired File Exchange. Bulk uploads now go through Seller Hub, Reports, Uploads.
B28: The header row of an upload file is tied to your account and to the template version, so a header typed from documentation can be rejected even when every value in it is right. Download your own template once, save it in this folder as ebay-template.csv, and the script will conform to it.
B29: Upload one card the first time. Read the results report. Then do the rest in bulk.

Sheet Summary
A1: Card Run HQ — where it stands
A2: MONEY OUT
A3: Spent on stock | B3: =N(SUM(Purchases!M2:M61)) | C3: Every row on Purchases, tax and shipping included.
A4: Spent on everything else | B4: =N(SUM(Expenses!E2:E61)) | C4: Supplies, postage, subscriptions — the Expenses tab.
A5: Total out of pocket | B5: =B3+B4 | C5: The real number, not the card cost.
A6: THE STOCK
A7: Cards on hand | B7: =N(SUMIFS(Inventory!X2:X61,Inventory!B2:B61,"Unlisted"))+N(SUMIFS(Inventory!X2:X61,Inventory!B2:B61,"Listed"))+N(SUMIFS(Inventory!X2:X61,Inventory!B2:B61,"Review")) | C7: Quantity, not rows — Unlisted, Listed and Review.
A8: What they cost | B8: =N(SUMPRODUCT(Inventory!X2:X61,Inventory!Y2:Y61)) | C8: Qty times cost each, across everything logged.
A9: What they are worth | B9: =N(SUMPRODUCT(Inventory!X2:X61,Inventory!Z2:Z61)) | C9: Qty times market value. A guess for sports; there is no free feed.
A10: Unrealised gain | B10: =B9-B8 | C10: Worth minus cost. Not money until it sells.
A11: WAITING ON YOU
A12: Held for review | B12: =COUNTIF(Inventory!B2:B61,"Review") | C12: Something on the card was uncertain. These cannot be exported.
A13: Ready to list | B13: =COUNTIF(Inventory!B2:B61,"Unlisted") | C13: What make_ebay_csv.py will pick up next run.
A14: Listed now | B14: =COUNTIF(Inventory!B2:B61,"Listed")
A15: MONEY IN
A16: Sold | B16: =COUNTA(Sales!B2:B301) | C16: Rows on the Sales tab.
A17: Gross | B17: =N(SUM(Sales!G2:G301)) | C17: Sale price plus what they paid to ship.
A18: Fees and postage | B18: =N(SUM(Sales!H2:H301))+N(SUM(Sales!I2:I301))+N(SUM(Sales!J2:J301))
A19: Net received | B19: =N(SUM(Sales!K2:K301))
A20: Profit on what sold | B20: =N(SUM(Sales!M2:M301)) | C20: Net minus what those cards cost.
A21: THE ANSWER
A22: Profit against everything spent | B22: =B20-B5 | C22: Sold profit minus every pound out. Negative until the stock turns over.
A23: Return on money spent | B23: =IF(N(B5)=0,"",B20/B5) | C23: Profit over spend. This is the number that says whether it works.
A25: Every number here is a formula over the other tabs. Nothing on this sheet is typed, so it cannot go stale — if a figure looks wrong, the row it came from is wrong.

Sheet Inventory
A1: SKU | B1: Status | C1: Date in | D1: Source | E1: Lot ID | F1: Category | G1: Sport or game | H1: League | I1: Year | J1: Brand / set | K1: Insert set | L1: Parallel | M1: Player or card name | N1: Card # | O1: Serial / | P1: Team | Q1: RC | R1: Auto | S1: Relic | T1: Graded by | U1: Grade | V1: Cert # | W1: Card condition | X1: Qty | Y1: Cost each | Z1: Market value | AA1: Ask price | AB1: Est fees | AC1: Est net | AD1: Margin | AE1: eBay title | AF1: Len | AG1: Sold comps | AH1: Notes
AB2: =ARRAYFORMULA(IF(AA2:AA="","",ROUND(AA2:AA*0.1325,2)+IF(AA2:AA<10,0.3,0.4))) | AC2: =ARRAYFORMULA(IF(AA2:AA="","",AA2:AA-AB2:AB)) | AD2: =ARRAYFORMULA(IF(AC2:AC="","",IF(Y2:Y="","",(AC2:AC-Y2:Y)/AC2:AC))) | AE2: =ARRAYFORMULA(IF(M2:M="","",TRIM(I2:I&" "&J2:J&" "&K2:K&" "&L2:L&" "&M2:M&IF(N2:N=""," "," #"&N2:N)&IF(O2:O=""," "," /"&O2:O)&IF(Q2:Q="Yes"," RC","")&IF(R2:R="Yes"," AUTO","")&IF(S2:S="Yes"," PATCH","")))) | AF2: =ARRAYFORMULA(IF(AE2:AE="","",LEN(AE2:AE))) | AG2: =ARRAYFORMULA(IF(M2:M="","",HYPERLINK("https://www.ebay.com/sch/i.html?_nkw="&SUBSTITUTE(TRIM(I2:I&" "&J2:J&" "&K2:K&" "&L2:L&" "&M2:M&" "&N2:N)," ","+")&"&_sacat=0&LH_Sold=1&LH_Complete=1&_ipg=100","sold")))

Sheet eBay upload
A1: Generated -- do not type here
A2: Run python make_ebay_csv.py and this tab is rebuilt from the Inventory rows marked Unlisted, alongside the CSV that gets uploaded.

Sheet Purchases
A1: Purchase ID | B1: Date | C1: Vendor / store | D1: Bought | E1: What | F1: Type | G1: Lot ID | H1: Qty | I1: Unit price | J1: Subtotal | K1: Tax | L1: Shipping | M1: Total paid | N1: Paid with | O1: Order / receipt # | P1: Receipt file | Q1: Notes
J2: =ARRAYFORMULA(IF(H2:H="","",H2:H*I2:I)) | M2: =ARRAYFORMULA(IF(J2:J="","",N(J2:J)+N(K2:K)+N(L2:L)))
A63: Everything you paid for, in one place.
A64: Subtotal and Total paid work themselves out -- type Qty, Unit price, Tax and Shipping. Lot ID ties a purchase to the cards that came out of it: put the same code on the Box log row and on every Inventory row from that box, and cost per card stops being a guess. Receipt file is just the filename you saved the photo or PDF under, e.g. receipts/2026-08-15-target.jpg. Keep the file; the tax year will want it and eBay will want it if a buyer disputes a sale. Supplies and postage go here too if you bought them as part of a trip; anything ongoing belongs on Expenses.

Sheet Box log
A1: Lot ID | B1: Date | C1: Time | D1: Store | E1: Location | F1: Product | G1: Qty | H1: Unit price | I1: Subtotal | J1: Tax | K1: Total paid | L1: List price | M1: Over / under list | N1: Cards pulled | O1: Cost per card | P1: Value pulled | Q1: Net vs cost | R1: Best hit | S1: Notes
A2: LOT-001 | B2: 46249 | D2: Big 5 | E2: Upland, CA | F2: 2025 Panini Prizm Draft Picks College Football - Mega Box | G2: 1 | H2: 69.99 | I2: =ARRAYFORMULA(IF(H2:H="","",G2:G*H2:H)) | J2: 5.42 | K2: =ARRAYFORMULA(IF(I2:I="","",I2:I+N(J2:J))) | L2: 55.99 | M2: =ARRAYFORMULA(IF(L2:L="","",K2:K-L2:L*N(G2:G))) | N2: 60 | O2: =ARRAYFORMULA(IF(N2:N="","",K2:K/N2:N)) | Q2: =ARRAYFORMULA(IF(P2:P="","",P2:P-K2:K)) | S2: 6 packs x 10 cards. 18 mega-box exclusives per box.

Sheet Expenses
A1: Date | B1: Category | C1: What | D1: Vendor | E1: Amount | F1: Paid with | G1: Receipt file | H1: Deductible | I1: Notes
A63: The costs that are not a card.
A64: Toploaders, sleeves, bubble mailers, stamps, the scanner, a subscription. These are what turn a gross profit into a real one, and they are the first thing forgotten. Anything bought as part of a buying trip can go on Purchases instead -- the Summary adds both, so it is counted once either way. Deductible is your call and worth marking as you go rather than reconstructing it in April.

Sheet Sales
A1: Date sold | B1: SKU | C1: What it was | D1: Channel | E1: Sale price | F1: Shipping charged | G1: Gross | H1: Fees | I1: Shipping cost | J1: Supplies | K1: Net | L1: Cost basis | M1: Profit | N1: Margin | O1: Notes
G2: =ARRAYFORMULA(IF(E2:E="","",E2:E+N(F2:F))) | K2: =ARRAYFORMULA(IF(G2:G="","",G2:G-N(H2:H)-N(I2:I)-N(J2:J))) | M2: =ARRAYFORMULA(IF(K2:K="","",K2:K-N(L2:L))) | N2: =ARRAYFORMULA(IF(K2:K="","",M2:M/K2:K))

Sheet Photos
A1: SKU | B1: Card | C1: Picture | D1: Front | E1: Back | F1: Extras | G1: How many | H1: Picture URL for eBay | I1: Checked | J1: Notes | L1: https://pthaiop587.github.io/tcg-scout/photos/
C2: =IF(A2="","",IFERROR(IMAGE($L$1&A2&".jpg",1),"no photo yet")) | D2: =IF(A2="","",A2&".jpg") | H2: =IF(A2="","",$L$1&A2&".jpg"&IF(E2="","","|"&$L$1&A2&"-back.jpg"))
C3: =IF(A3="","",IFERROR(IMAGE($L$1&A3&".jpg",1),"no photo yet")) | D3: =IF(A3="","",A3&".jpg") | H3: =IF(A3="","",$L$1&A3&".jpg"&IF(E3="","","|"&$L$1&A3&"-back.jpg"))
C4: =IF(A4="","",IFERROR(IMAGE($L$1&A4&".jpg",1),"no photo yet")) | D4: =IF(A4="","",A4&".jpg") | H4: =IF(A4="","",$L$1&A4&".jpg"&IF(E4="","","|"&$L$1&A4&"-back.jpg"))
C5: =IF(A5="","",IFERROR(IMAGE($L$1&A5&".jpg",1),"no photo yet")) | D5: =IF(A5="","",A5&".jpg") | H5: =IF(A5="","",$L$1&A5&".jpg"&IF(E5="","","|"&$L$1&A5&"-back.jpg"))
C6: =IF(A6="","",IFERROR(IMAGE($L$1&A6&".jpg",1),"no photo yet")) | D6: =IF(A6="","",A6&".jpg") | H6: =IF(A6="","",$L$1&A6&".jpg"&IF(E6="","","|"&$L$1&A6&"-back.jpg"))
C7: =IF(A7="","",IFERROR(IMAGE($L$1&A7&".jpg",1),"no photo yet")) | D7: =IF(A7="","",A7&".jpg") | H7: =IF(A7="","",$L$1&A7&".jpg"&IF(E7="","","|"&$L$1&A7&"-back.jpg"))
C8: =IF(A8="","",IFERROR(IMAGE($L$1&A8&".jpg",1),"no photo yet")) | D8: =IF(A8="","",A8&".jpg") | H8: =IF(A8="","",$L$1&A8&".jpg"&IF(E8="","","|"&$L$1&A8&"-back.jpg"))
C9: =IF(A9="","",IFERROR(IMAGE($L$1&A9&".jpg",1),"no photo yet")) | D9: =IF(A9="","",A9&".jpg") | H9: =IF(A9="","",$L$1&A9&".jpg"&IF(E9="","","|"&$L$1&A9&"-back.jpg"))
C10: =IF(A10="","",IFERROR(IMAGE($L$1&A10&".jpg",1),"no photo yet")) | D10: =IF(A10="","",A10&".jpg") | H10: =IF(A10="","",$L$1&A10&".jpg"&IF(E10="","","|"&$L$1&A10&"-back.jpg"))
C11: =IF(A11="","",IFERROR(IMAGE($L$1&A11&".jpg",1),"no photo yet")) | D11: =IF(A11="","",A11&".jpg") | H11: =IF(A11="","",$L$1&A11&".jpg"&IF(E11="","","|"&$L$1&A11&"-back.jpg"))
C12: =IF(A12="","",IFERROR(IMAGE($L$1&A12&".jpg",1),"no photo yet")) | D12: =IF(A12="","",A12&".jpg") | H12: =IF(A12="","",$L$1&A12&".jpg"&IF(E12="","","|"&$L$1&A12&"-back.jpg"))
C13: =IF(A13="","",IFERROR(IMAGE($L$1&A13&".jpg",1),"no photo yet")) | D13: =IF(A13="","",A13&".jpg") | H13: =IF(A13="","",$L$1&A13&".jpg"&IF(E13="","","|"&$L$1&A13&"-back.jpg"))
... C41: =IF(A41="","",IFERROR(IMAGE($L$1&A41&".jpg",1),"no photo yet")) | D41: =IF(A41="","",A41&".jpg") | H41: =IF(A41="","",$L$1&A41&".jpg"&IF(E41="","","|"&$L$1&A41&"-back.jpg"))
A63: What each card actually has a picture of.
A64: In the Google copy this tab fills itself: type a SKU in column A and the photograph appears, live, off the published site. In the Excel copy it is filled in by python embed_photos.py -- it reads the photos folder, writes a row per SKU and puts the thumbnail in the Picture column, so this tab is the visual stock check. Re-run it whenever you add photos; it rewrites the tab from what is on disk. The URL column is the address eBay will fetch. It only resolves once the photos have been pushed and published -- the workbook carries links, never the image files themselves, because eBay needs a public https address rather than an embedded picture. A card with no row here has no photograph yet.

Sheet Audit
A1: Audit — what to fix before it costs you
A3: STOPS A LISTING
A4: Cards held for review | B4: =COUNTIF(Inventory!B2:B61,"Review") | C4: Something was uncertain when it was filed — usually the parallel or the value. make_ebay_csv.py skips these on purpose. Settle the CHECK note in Notes, then set Status to Unlisted.
A5: Ready to list but worth nothing | B5: =SUMPRODUCT((Inventory!B2:B61="Unlisted")*(N(Inventory!Z2:Z61)=0)) | C5: It will export at a price of nothing. Put a market value on it, or move it to Review until you have one.
A6: Ready to list with no photo | B6: =SUMPRODUCT((Inventory!B2:B61="Unlisted")*(COUNTIF(Photos!A2:A61,Inventory!A2:A61)=0)) | C6: eBay needs a picture. Run embed_photos.py after adding photos so this tab knows about them.
A7: Titles over 80 characters | B7: =SUMPRODUCT((N(Inventory!AF2:AF61)>80)*1) | C7: eBay truncates at 80. The Len column on Inventory shows each one.
A8: COSTS YOU MONEY
A9: Cards with no cost recorded | B9: =SUMPRODUCT((LEN(Inventory!A2:A61)>0)*(N(Inventory!Y2:Y61)=0)) | C9: Profit on a sale is meaningless without it, and so is the Summary. If a card came out of a box, put the box's Lot ID on it and use cost per card from the Box log.
A10: Cards with no Lot ID | B10: =SUMPRODUCT((LEN(Inventory!A2:A61)>0)*(LEN(Inventory!E2:E61)=0)) | C10: Nothing ties them back to a purchase, so you cannot tell which box paid for itself.
A11: Purchases with no receipt file | B11: =SUMPRODUCT((LEN(Purchases!A2:A61)>0)*(LEN(Purchases!P2:P61)=0)) | C11: The tax year will want them, and so will eBay if a buyer disputes.
A12: Sales with no cost basis | B12: =SUMPRODUCT((LEN(Sales!B2:B301)>0)*(N(Sales!L2:L301)=0)) | C12: Profit on those rows is overstated by exactly what the card cost.
A13: PROBABLY A MISTAKE
A14: Duplicate SKUs | B14: =SUMPRODUCT((LEN(Inventory!A2:A61)>0)*(COUNTIF(Inventory!A2:A61,Inventory!A2:A61&"")>1)) | C14: A SKU is meant to be one physical card. Two rows sharing one means photos and sales will attach to whichever Excel finds first.
A15: Serial numbered with quantity over 1 | B15: =SUMPRODUCT((LEN(Inventory!O2:O61)>0)*(N(Inventory!X2:X61)>1)) | C15: A numbered card is one of one at that number. Two of them is two different cards and wants two rows.
A16: Graded with no cert number | B16: =SUMPRODUCT((LEN(Inventory!T2:T61)>0)*(LEN(Inventory!V2:V61)=0)) | C16: Buyers check the cert. eBay has a field for it.
A17: Sold but still Unlisted or Listed | B17: =SUMPRODUCT((COUNTIF(Sales!B2:B301,Inventory!A2:A61)>0)*(Inventory!B2:B61<>"Sold")) | C17: It is on the Sales tab but the stock still thinks you have it. That is how a card gets listed twice.
A19: Every count is a formula, so this tab is never out of date. A zero down the whole column means the workbook is clean. None of it blocks anything — it is a list of things that are cheap to fix now and expensive to find out about from a buyer.

Sheet Reference
A1: eBay codes, checked August 2026
A3: Category
A4: What | B4: Code | C4: Notes
A5: Sports card singles | B5: 261328 | C5: Football, basketball, baseball, hockey, soccer. Sport goes in its own item specific.
A6: Non-sport card singles | B6: 183050 | C6: Garbage Pail Kids, movie and TV cards.
A7: CCG individual cards | B7: 183454 | C7: Pokemon, Magic, Lorcana, One Piece, Yu-Gi-Oh.
A9: Condition ID
A10: What | B10: Code | C10: Notes
A11: Graded | B11: 2750 | C11: Slabbed by a grading company. Grader, grade and cert number then become required.
A12: Ungraded | B12: 4000 | C12: Raw card. Needs the card condition descriptor below. 'Used' is no longer accepted for cards.
A14: Card condition descriptor -- CD:Card Condition (ID: 40001)
A15: What | B15: Code | C15: Notes
A16: Near Mint or Better | B16: 400010 | C16: Required on every ungraded card since 2023.
A17: Excellent | B17: 400011 | C17: Required on every ungraded card since 2023.
A18: Very Good | B18: 400012 | C18: Required on every ungraded card since 2023.
A19: Poor | B19: 400013 | C19: Required on every ungraded card since 2023.
A21: Professional grader -- CD:Professional Grader (ID: 27501)
A22: What | B22: Code | C22: Notes
A23: Professional Sports Authenticator (PSA) | C23: Graded cards only. Grade goes in ID 27502, cert number in ID 27503.
A24: Beckett Grading Services (BGS) | C24: Graded cards only. Grade goes in ID 27502, cert number in ID 27503.
A25: Sportscard Guaranty Corporation (SGC) | C25: Graded cards only. Grade goes in ID 27502, cert number in ID 27503.
A26: Certified Guaranty Company (CGC) | C26: Graded cards only. Grade goes in ID 27502, cert number in ID 27503.
A27: Hybrid Grading Approach (HGA) | C27: Graded cards only. Grade goes in ID 27502, cert number in ID 27503.
A28: Technical Authentication & Grading (TAG) | C28: Graded cards only. Grade goes in ID 27502, cert number in ID 27503.
A29: Other | C29: Graded cards only. Grade goes in ID 27502, cert number in ID 27503.
A31: Fees used by the formulas
A32: What | B32: Code | C32: Notes
A33: eBay final value fee | B33: 13.25% | C33: Trading cards, charged on the item plus the shipping the buyer pays.
A34: eBay per-order fee | B34: $0.30 / $0.40 | C34: $0.30 when the order is under $10, otherwise $0.40.
A35: eBay insertion | B35: $0.35 | C35: Only past the 250 free listings a month.
A36: eBay Standard Envelope | B36: $0.74 - $1.32 | C36: Raw cards under $20. Tracked, and the cheapest way to move a single.
A37: TCGplayer | B37: 10.75% + 2.5% + $0.30 | C37: The $0.30 is per order, not per card, so a cart of singles amortises it. TCG only.
A38: COMC | B38: 5% + 10% cash out | C38: Plus roughly $0.50-1.00 a card to submit. Worth it on volumes of cheap sports singles.
A40: Where these came from
A41: What | B41: Code | C41: Notes
A42: Condition IDs and descriptors | C42: eBay Developers, Condition Descriptor IDs; eBay community thread on Seller Hub reports for trading card ungraded values.
A43: Category IDs | C43: eBay's own browse URLs, e.g. ebay.com/b/Trading-Card-Singles/261328.
A44: Bulk upload route | C44: File Exchange is retired. Uploads now go through Seller Hub, Reports, Uploads.
A45: Header row | C45: The header row is tied to your account and template version. Download the template from your own Seller Hub and let make_ebay_csv.py match it.

Sheet Lists
A1: Graders | C1: Card conditions
A2: Professional Sports Authenticator (PSA) | C2: Near Mint or Better
A3: Beckett Grading Services (BGS) | C3: Excellent
A4: Sportscard Guaranty Corporation (SGC) | C4: Very Good
A5: Certified Guaranty Company (CGC) | C5: Poor
A6: Hybrid Grading Approach (HGA)
A7: Technical Authentication & Grading (TAG)
A8: Other
